pyExtendedConfigParser/__init__.py
test/__init__.py
test/test_1/Test.py
test/test_1/__init__.py
test/test_2/Test.py
test/test_2/__init__.py
test/test_3/Test.py
test/test_3/__init__.py
test/test_4/Test.py
test/test_4/__init__.py
test/test_5/Test.py
test/test_5/__init__.py
test/test_6/Test.py
test/test_6/__init__.py
pyExtendedConfigParser-1.1.2.dist-info/LICENSE.md
pyExtendedConfigParser-1.1.2.dist-info/METADATA
pyExtendedConfigParser-1.1.2.dist-info/WHEEL
pyExtendedConfigParser-1.1.2.dist-info/top_level.txt
pyExtendedConfigParser-1.1.2.dist-info/RECORD
