Metadata-Version: 2.1
Name: pyExtendedConfigParser
Version: 1.1.2
Summary: An extended ConfigParser based on Python's ConfigParser.
Home-page: https://github.com/Paebbels/pyExtendedConfigParser
Author: Patrick Lehmann
Author-email: Paebbels@gmail.com
License: UNKNOWN
Project-URL: Documentation, https://pyExtendedConfigParser.readthedocs.io/en/latest/
Project-URL: Source Code, https://github.com/Paebbels/pyExtendedConfigParser
Project-URL: Issue Tracker, https://github.com/Paebbels/pyExtendedConfigParser/issues
Keywords: Python3 Path Generic-Library
Platform: UNKNOWN
Classifier: License :: OSI Approved :: Apache Software License
Classifier: Operating System :: OS Independent
Classifier: Programming Language :: Python :: 3 :: Only
Classifier: Programming Language :: Python :: 3.4
Classifier: Programming Language :: Python :: 3.5
Classifier: Programming Language :: Python :: 3.6
Classifier: Programming Language :: Python :: 3.7
Classifier: Programming Language :: Python :: 3.8
Classifier: Development Status :: 5 - Production/Stable
Classifier: Intended Audience :: Developers
Classifier: Topic :: Utilities
Requires-Python: >=3.4
